README.rst
setup.cfg
setup.py
blessedblocks/__init__.py
blessedblocks/block.py
blessedblocks/blocks.py
blessedblocks/line.py
blessedblocks/runner.py
blessedblocks/stacktracer.py
blessedblocks.egg-info/PKG-INFO
blessedblocks.egg-info/SOURCES.txt
blessedblocks.egg-info/dependency_links.txt
blessedblocks.egg-info/not-zip-safe
blessedblocks.egg-info/requires.txt
blessedblocks.egg-info/top_level.txt
tests/__init__.py
tests/test_block.py
tests/test_divvy.py
tests/test_hfill.py
tests/test_line.py
tests/test_vfill.py
tests/test_xxx.py